_postgresql
pgembed
