Metadata-Version: 2.4
Name: pgembed
Version: 0.1.6
Summary: Self-contained postgres server for your python applications
Author-email: Oscar Moll <orm@csail.mit.edu>, Arun Sharma <arun@sharma-home.net>
Project-URL: repository, https://github.com/Ladybug-Memory/pgembed
Keywords: postgresql,pgvector,pgembed,rag
Requires-Python: >=3.12
License-File: LICENSE
Requires-Dist: fasteners>=0.19
Requires-Dist: platformdirs>=4.0.0
Requires-Dist: psutil>=5.9.0
Provides-Extra: dev
Requires-Dist: sysv_ipc; extra == "dev"
Provides-Extra: test
Requires-Dist: pytest; extra == "test"
Requires-Dist: psycopg2-binary; extra == "test"
Requires-Dist: sqlalchemy>=2; extra == "test"
Requires-Dist: sqlalchemy-utils; extra == "test"
Dynamic: license-file
